pyadbbackup/__init__.py
pyadbbackup/__main__.py
pyadbbackup/backup.py
pyadbbackup/exceptions.py
pyadbbackup/main.py
pyadbbackup/partition.py
pyadbbackup-0.1.2.dist-info/LICENSE
pyadbbackup-0.1.2.dist-info/METADATA
pyadbbackup-0.1.2.dist-info/WHEEL
pyadbbackup-0.1.2.dist-info/RECORD
